setup.py
django_places.egg-info/PKG-INFO
django_places.egg-info/SOURCES.txt
django_places.egg-info/dependency_links.txt
django_places.egg-info/requires.txt
django_places.egg-info/top_level.txt
places/__init__.py
places/admin.py
places/exceptions.py
places/forms.py
places/functions.py
places/models.py
places/urls.py
places/views.py