Metadata-Version: 1.0
Name: django-places
Version: 0.1
Summary: Place or Location management app for django
Home-page: http://github.com/shelfworthy/django-places
Author: Chris Drackett
Author-email: chris@shelfworthy.com
License: UNKNOWN
Platform: UNKNOWN
Classifier: Development Status :: 2 - Pre-Alpha
Classifier: Environment :: Web Environment
Classifier: Intended Audience :: Developers
Classifier: Natural Language :: English
Classifier: License :: OSI Approved :: BSD License
Classifier: Operating System :: OS Independent
Classifier: Programming Language :: Python
Classifier: Framework :: Django
Classifier: Topic :: Utilities
